casting/apps/cast/tui/__init__.py
casting/apps/cast/tui/app.py
cast_tui-0.1.0.dist-info/WHEEL
cast_tui-0.1.0.dist-info/METADATA
cast_tui-0.1.0.dist-info/RECORD
