Metadata-Version: 2.3
Name: cast-tui
Version: 0.1.0
Summary: Minimal, extensible terminal (TUI) framework with fuzzy autocomplete and plugin API
Requires-Dist: prompt-toolkit>=3.0.43
Requires-Dist: rich>=13.0.0
Requires-Dist: pytest>=8.3.0 ; extra == 'dev'
Requires-Python: >=3.13
Provides-Extra: dev
